{
    "domain": "photobucket.com",
    "owner": {},
    "source": [
        "DuckDuckGo-CA"
    ],
    "prevalence": 0.00161,
    "sites": 16,
    "subdomains": [
        "i155"
    ],
    "cnames": [],
    "fingerprinting": 0,
    "resources": [
        {
            "rule": "photobucket\\.com\\/albums\\/s282\\/theviejo\\/recurso_9_1\\.jpg",
            "cookies": 0,
            "fingerprinting": 0,
            "subdomains": [
                "i155"
            ],
            "apis": {},
            "sites": 2,
            "prevalence": 0.000201,
            "cnames": [],
            "responseHashes": [
                "c69b575b309970d80d884dea680a573b0f4022ccbc37da29211d55bbac765c8d"
            ],
            "type": "Image",
            "firstPartyCookies": {},
            "firstPartyCookiesSent": {},
            "exampleSites": [
                "abgcrot.life",
                "mamicrot.fun"
            ]
        },
        {
            "rule": "photobucket\\.com\\/albums\\/s282\\/theviejo\\/recurso_10_1\\.jpg",
            "cookies": 0,
            "fingerprinting": 0,
            "subdomains": [
                "i155"
            ],
            "apis": {},
            "sites": 9,
            "prevalence": 0.000904,
            "cnames": [],
            "responseHashes": [
                "d5cc8c57ca94aa77dec165817d37fc942c1dbefdbd80317fa88a3fc489aa0f4a"
            ],
            "type": "Image",
            "firstPartyCookies": {},
            "firstPartyCookiesSent": {},
            "exampleSites": [
                "cewekgenit.one",
                "indocabe.info",
                "jambulmemek.me",
                "memeksiana.top",
                "mukacrot.life",
                "pornogrim.com",
                "tantemalam.info",
                "tantenakal.top",
                "videobokep17.sbs"
            ]
        },
        {
            "rule": "photobucket\\.com\\/albums\\/s282\\/theviejo\\/recurso_3_1\\.jpg",
            "cookies": 0,
            "fingerprinting": 0,
            "subdomains": [
                "i155"
            ],
            "apis": {},
            "sites": 2,
            "prevalence": 0.000201,
            "cnames": [],
            "responseHashes": [
                "0ba4bd207a7b1f8a6e384cf2c1eed084dfb9a223042690abc1750cd5e1753207"
            ],
            "type": "Image",
            "firstPartyCookies": {},
            "firstPartyCookiesSent": {},
            "exampleSites": [
                "memekviral.top",
                "ngeweyuk.life"
            ]
        }
    ],
    "categories": [],
    "performance": {},
    "cookies": 0,
    "topInitiators": [
        {
            "domain": "first party",
            "prevalence": 0.75
        },
        {
            "domain": "abgcrot.info",
            "prevalence": 0.0625
        },
        {
            "domain": "cewekgenit.info",
            "prevalence": 0.0625
        },
        {
            "domain": "ajax.googleapis.com",
            "prevalence": 0.0625
        },
        {
            "domain": "pornogrim.link",
            "prevalence": 0.0625
        }
    ],
    "types": {
        "Image": 13
    },
    "nameservers": [
        "ns-56.awsdns-07.com",
        "ns-930.awsdns-52.net",
        "ns-1887.awsdns-43.co.uk",
        "ns-1454.awsdns-53.org"
    ]
}