{
    "domain": "avocet.io",
    "owner": {
        "name": "Avocet Systems Ltd.",
        "displayName": "Avocet Systems",
        "privacyPolicy": "https://avocet.io/privacy-portal",
        "url": "http://avocet.io"
    },
    "source": [
        "DuckDuckGo-GB"
    ],
    "prevalence": 0.00341,
    "sites": 34,
    "subdomains": [
        "ads"
    ],
    "cnames": [],
    "fingerprinting": 0,
    "resources": [
        {
            "rule": "avocet\\.io\\/s",
            "cookies": 0,
            "fingerprinting": 0,
            "subdomains": [
                "ads"
            ],
            "apis": {},
            "sites": 14,
            "prevalence": 0.0014,
            "cnames": [],
            "responseHashes": [],
            "type": "Image",
            "firstPartyCookies": {},
            "firstPartyCookiesSent": {},
            "exampleSites": [
                "bikeradar.com",
                "forum.gardenersworld.com",
                "www.arts.ac.uk",
                "www.bikeradar.com",
                "www.discoverwildlife.com",
                "www.findaphd.com",
                "www.gardenersworld.com",
                "www.gardensillustrated.com",
                "www.historyextra.com",
                "www.madeformums.com",
                "www.olivemagazine.com",
                "www.radiotimes.com",
                "www.sciencefocus.com",
                "www.themortgageworks.co.uk"
            ]
        },
        {
            "rule": "avocet\\.io\\/s",
            "cookies": 0,
            "fingerprinting": 0,
            "subdomains": [
                "ads"
            ],
            "apis": {},
            "sites": 10,
            "prevalence": 0.001,
            "cnames": [],
            "responseHashes": [],
            "type": "Script",
            "firstPartyCookies": {},
            "firstPartyCookiesSent": {
                "__rmc__": 0.00010032102728731942
            },
            "exampleSites": [
                "road.cc",
                "www.aarp.org",
                "www.betfred.com",
                "www.ecb.co.uk",
                "www.fineandcountry.com",
                "www.kuoni.co.uk",
                "www.malwarebytes.com",
                "www.nationaltheatre.org.uk",
                "www.royalhighlandshow.org",
                "www.rspca.org.uk"
            ]
        },
        {
            "rule": "avocet\\.io\\/getuid",
            "cookies": 0,
            "fingerprinting": 0,
            "subdomains": [
                "ads"
            ],
            "apis": {},
            "sites": 9,
            "prevalence": 0.000903,
            "cnames": [],
            "responseHashes": [
                "1866961a029c65376fefb7f2ba1e6187e09ff50ea58d97dedfd72c197947d002"
            ],
            "type": "Image",
            "firstPartyCookies": {},
            "firstPartyCookiesSent": {},
            "exampleSites": [
                "ladbrokes.com",
                "sports.coral.co.uk",
                "thephonebook.bt.com",
                "www.coral.co.uk",
                "www.foxybingo.com",
                "www.galaspins.com",
                "www.galabingo.com",
                "www.ladbrokes.com",
                "www.thephonebook.bt.com"
            ]
        }
    ],
    "categories": [
        "Ad Motivated Tracking",
        "Advertising",
        "Ad Fraud",
        "Audience Measurement"
    ],
    "performance": {},
    "cookies": 0,
    "types": {
        "Image": 23,
        "Script": 10
    },
    "nameservers": [
        "ns-883.awsdns-46.net",
        "ns-473.awsdns-59.com",
        "ns-1723.awsdns-23.co.uk",
        "ns-1107.awsdns-10.org"
    ]
}