{
    "domain": "ebay.com.edgekey.net",
    "owner": {
        "name": "Akamai Technologies",
        "displayName": "Akamai",
        "privacyPolicy": "https://www.akamai.com/us/en/privacy-policies/",
        "url": "http://akamai.com"
    },
    "source": [
        "DuckDuckGo-GB"
    ],
    "prevalence": 0.000702,
    "sites": 7,
    "subdomains": [
        "slot9428",
        "slot11847"
    ],
    "cnames": [
        {
            "original": "pages.ebay.ca",
            "resolved": "slot11847.ebay.com.edgekey.net"
        },
        {
            "original": "pages.ebay.com.au",
            "resolved": "slot11847.ebay.com.edgekey.net"
        },
        {
            "original": "rover.ebay.co.uk",
            "resolved": "slot9428.ebay.com.edgekey.net"
        },
        {
            "original": "rover.ebay.com.au",
            "resolved": "slot9428.ebay.com.edgekey.net"
        },
        {
            "original": "rover.ebay.de",
            "resolved": "slot9428.ebay.com.edgekey.net"
        }
    ],
    "fingerprinting": 0,
    "resources": [
        {
            "rule": "ebay\\.com\\.edgekey\\.net\\/roverimp\\/0\\/0\\/9",
            "cookies": 0.000401,
            "fingerprinting": 0,
            "subdomains": [
                "slot9428"
            ],
            "apis": {},
            "sites": 4,
            "prevalence": 0.000401,
            "cnames": [
                {
                    "original": "rover.ebay.co.uk",
                    "resolved": "slot9428.ebay.com.edgekey.net"
                },
                {
                    "original": "rover.ebay.com.au",
                    "resolved": "slot9428.ebay.com.edgekey.net"
                },
                {
                    "original": "rover.ebay.de",
                    "resolved": "slot9428.ebay.com.edgekey.net"
                }
            ],
            "responseHashes": [
                "9bb0cd4cf48cc03f6567cbcbb2ab40ee8ab022ae654c4577c83625add32c997b"
            ],
            "type": "Image",
            "firstPartyCookies": {},
            "firstPartyCookiesSent": {},
            "exampleSites": [
                "ebay.co.uk",
                "www.ebay.co.uk",
                "www.ebay.com.au",
                "www.ebay.de"
            ]
        },
        {
            "rule": "ebay\\.com\\.edgekey\\.net\\/roversync\\/",
            "cookies": 0.000401,
            "fingerprinting": 0,
            "subdomains": [
                "slot9428"
            ],
            "apis": {},
            "sites": 4,
            "prevalence": 0.000401,
            "cnames": [
                {
                    "original": "rover.ebay.co.uk",
                    "resolved": "slot9428.ebay.com.edgekey.net"
                },
                {
                    "original": "rover.ebay.com.au",
                    "resolved": "slot9428.ebay.com.edgekey.net"
                },
                {
                    "original": "rover.ebay.de",
                    "resolved": "slot9428.ebay.com.edgekey.net"
                }
            ],
            "responseHashes": [
                "9bb0cd4cf48cc03f6567cbcbb2ab40ee8ab022ae654c4577c83625add32c997b"
            ],
            "type": "Image",
            "firstPartyCookies": {},
            "firstPartyCookiesSent": {},
            "exampleSites": [
                "ebay.co.uk",
                "www.ebay.co.uk",
                "www.ebay.com.au",
                "www.ebay.de"
            ]
        },
        {
            "rule": "ebay\\.com\\.edgekey\\.net\\/rtm_default\\/1200\\/19392\\.html",
            "cookies": 0.000201,
            "fingerprinting": 0,
            "subdomains": [
                "slot11847"
            ],
            "apis": {},
            "sites": 2,
            "prevalence": 0.000201,
            "cnames": [
                {
                    "original": "pages.ebay.ca",
                    "resolved": "slot11847.ebay.com.edgekey.net"
                },
                {
                    "original": "pages.ebay.com.au",
                    "resolved": "slot11847.ebay.com.edgekey.net"
                }
            ],
            "responseHashes": [
                "8c006f9c1ca9f61efd92ed7183abbe51a85dc4cf6b5e066cca8c231e7f974304"
            ],
            "type": "Document",
            "firstPartyCookies": {},
            "firstPartyCookiesSent": {},
            "exampleSites": [
                "ebay.ca",
                "www.ebay.com.au"
            ]
        },
        {
            "rule": "ebay\\.com\\.edgekey\\.net\\/rtm_default\\/1200\\/19393\\.html",
            "cookies": 0.000201,
            "fingerprinting": 0,
            "subdomains": [
                "slot11847"
            ],
            "apis": {},
            "sites": 2,
            "prevalence": 0.000201,
            "cnames": [
                {
                    "original": "pages.ebay.ca",
                    "resolved": "slot11847.ebay.com.edgekey.net"
                },
                {
                    "original": "pages.ebay.com.au",
                    "resolved": "slot11847.ebay.com.edgekey.net"
                }
            ],
            "responseHashes": [
                "56e82d1ead98408a540921aea73ceb24c14c7d5b72b944f9379823d1692a1d9d"
            ],
            "type": "Document",
            "firstPartyCookies": {},
            "firstPartyCookiesSent": {},
            "exampleSites": [
                "ebay.ca",
                "www.ebay.com.au"
            ]
        },
        {
            "rule": "ebay\\.com\\.edgekey\\.net\\/rtm_default\\/1200\\/19394\\.html",
            "cookies": 0.000201,
            "fingerprinting": 0,
            "subdomains": [
                "slot11847"
            ],
            "apis": {},
            "sites": 2,
            "prevalence": 0.000201,
            "cnames": [
                {
                    "original": "pages.ebay.ca",
                    "resolved": "slot11847.ebay.com.edgekey.net"
                },
                {
                    "original": "pages.ebay.com.au",
                    "resolved": "slot11847.ebay.com.edgekey.net"
                }
            ],
            "responseHashes": [
                "68620c81d9ffbe66becdcd2de35f3f3f353a484f59df715af6388eb35efa4776"
            ],
            "type": "Document",
            "firstPartyCookies": {},
            "firstPartyCookiesSent": {},
            "exampleSites": [
                "ebay.ca",
                "www.ebay.com.au"
            ]
        },
        {
            "rule": "ebay\\.com\\.edgekey\\.net\\/rtm_default\\/1200\\/19395\\.html",
            "cookies": 0.000201,
            "fingerprinting": 0,
            "subdomains": [
                "slot11847"
            ],
            "apis": {},
            "sites": 2,
            "prevalence": 0.000201,
            "cnames": [
                {
                    "original": "pages.ebay.ca",
                    "resolved": "slot11847.ebay.com.edgekey.net"
                },
                {
                    "original": "pages.ebay.com.au",
                    "resolved": "slot11847.ebay.com.edgekey.net"
                }
            ],
            "responseHashes": [
                "656dec805ba68011e9c23db2afaff1a3a761a9e309fa65e04d780f6e4d8fe83f"
            ],
            "type": "Document",
            "firstPartyCookies": {},
            "firstPartyCookiesSent": {},
            "exampleSites": [
                "ebay.ca",
                "www.ebay.com.au"
            ]
        },
        {
            "rule": "ebay\\.com\\.edgekey\\.net\\/rtm_default\\/1200\\/19396\\.html",
            "cookies": 0.000201,
            "fingerprinting": 0,
            "subdomains": [
                "slot11847"
            ],
            "apis": {},
            "sites": 2,
            "prevalence": 0.000201,
            "cnames": [
                {
                    "original": "pages.ebay.ca",
                    "resolved": "slot11847.ebay.com.edgekey.net"
                },
                {
                    "original": "pages.ebay.com.au",
                    "resolved": "slot11847.ebay.com.edgekey.net"
                }
            ],
            "responseHashes": [
                "c3ec613a1723fea9a51f78f1c2bee0508d885dcd8f961c359dae41c4df543ae9"
            ],
            "type": "Document",
            "firstPartyCookies": {},
            "firstPartyCookiesSent": {},
            "exampleSites": [
                "ebay.ca",
                "www.ebay.com.au"
            ]
        },
        {
            "rule": "ebay\\.com\\.edgekey\\.net\\/rtm_default\\/1200\\/19397\\.html",
            "cookies": 0.000201,
            "fingerprinting": 0,
            "subdomains": [
                "slot11847"
            ],
            "apis": {},
            "sites": 2,
            "prevalence": 0.000201,
            "cnames": [
                {
                    "original": "pages.ebay.ca",
                    "resolved": "slot11847.ebay.com.edgekey.net"
                },
                {
                    "original": "pages.ebay.com.au",
                    "resolved": "slot11847.ebay.com.edgekey.net"
                }
            ],
            "responseHashes": [
                "dd499e7eabe62d9cabc89fb2b1a789be282dc5f8eb49bffec98c12bbd9a7406a"
            ],
            "type": "Document",
            "firstPartyCookies": {},
            "firstPartyCookiesSent": {},
            "exampleSites": [
                "ebay.ca",
                "www.ebay.com.au"
            ]
        },
        {
            "rule": "ebay\\.com\\.edgekey\\.net\\/rtm_default\\/1200\\/19398\\.html",
            "cookies": 0.000201,
            "fingerprinting": 0,
            "subdomains": [
                "slot11847"
            ],
            "apis": {},
            "sites": 2,
            "prevalence": 0.000201,
            "cnames": [
                {
                    "original": "pages.ebay.ca",
                    "resolved": "slot11847.ebay.com.edgekey.net"
                },
                {
                    "original": "pages.ebay.com.au",
                    "resolved": "slot11847.ebay.com.edgekey.net"
                }
            ],
            "responseHashes": [
                "7601a423dceb3db36633782ce33499c79b1bf81418a73de86676fb81352eb7e9"
            ],
            "type": "Document",
            "firstPartyCookies": {},
            "firstPartyCookiesSent": {},
            "exampleSites": [
                "ebay.ca",
                "www.ebay.com.au"
            ]
        },
        {
            "rule": "ebay\\.com\\.edgekey\\.net\\/rtm_default\\/1200\\/19399\\.html",
            "cookies": 0.000201,
            "fingerprinting": 0,
            "subdomains": [
                "slot11847"
            ],
            "apis": {},
            "sites": 2,
            "prevalence": 0.000201,
            "cnames": [
                {
                    "original": "pages.ebay.ca",
                    "resolved": "slot11847.ebay.com.edgekey.net"
                },
                {
                    "original": "pages.ebay.com.au",
                    "resolved": "slot11847.ebay.com.edgekey.net"
                }
            ],
            "responseHashes": [
                "bd2ff1499262029267657a8de64c6c1f9bc1144338fb7af8b336ed17f2430d8f"
            ],
            "type": "Document",
            "firstPartyCookies": {},
            "firstPartyCookiesSent": {},
            "exampleSites": [
                "ebay.ca",
                "www.ebay.com.au"
            ]
        },
        {
            "rule": "ebay\\.com\\.edgekey\\.net\\/rtm_default\\/1200\\/19400\\.html",
            "cookies": 0.000201,
            "fingerprinting": 0,
            "subdomains": [
                "slot11847"
            ],
            "apis": {},
            "sites": 2,
            "prevalence": 0.000201,
            "cnames": [
                {
                    "original": "pages.ebay.ca",
                    "resolved": "slot11847.ebay.com.edgekey.net"
                },
                {
                    "original": "pages.ebay.com.au",
                    "resolved": "slot11847.ebay.com.edgekey.net"
                }
            ],
            "responseHashes": [
                "abce1230e42b409df7d28ab1d9301a65c9ad1e60f8c56a582df72ded37980cd2"
            ],
            "type": "Document",
            "firstPartyCookies": {},
            "firstPartyCookiesSent": {},
            "exampleSites": [
                "ebay.ca",
                "www.ebay.com.au"
            ]
        },
        {
            "rule": "ebay\\.com\\.edgekey\\.net\\/rtm_default\\/1200\\/19401\\.html",
            "cookies": 0.0001,
            "fingerprinting": 0,
            "subdomains": [
                "slot11847"
            ],
            "apis": {},
            "sites": 2,
            "prevalence": 0.000201,
            "cnames": [
                {
                    "original": "pages.ebay.ca",
                    "resolved": "slot11847.ebay.com.edgekey.net"
                },
                {
                    "original": "pages.ebay.com.au",
                    "resolved": "slot11847.ebay.com.edgekey.net"
                }
            ],
            "responseHashes": [
                "db30bfcb448ca28bb16e12baa994b5b6b9a4a6e18c455456f73065b40b5230b1"
            ],
            "type": "Document",
            "firstPartyCookies": {},
            "firstPartyCookiesSent": {},
            "exampleSites": [
                "ebay.ca",
                "www.ebay.com.au"
            ]
        }
    ],
    "categories": [],
    "performance": {},
    "cookies": 0.000502,
    "types": {
        "Image": 8,
        "Document": 20
    },
    "nameservers": []
}