{
    "domain": "exdynsrv.com",
    "owner": {
        "name": "ExoClick, S.L.",
        "displayName": "ExoClick",
        "privacyPolicy": "https://www.exoclick.com/privacy/",
        "url": "http://exoclick.com"
    },
    "source": [
        "DuckDuckGo-US"
    ],
    "prevalence": 0.000905,
    "sites": 133,
    "subdomains": [
        "a",
        "syndication"
    ],
    "cnames": [],
    "fingerprinting": 2,
    "resources": [
        {
            "rule": "exdynsrv\\.com\\/nativeads-v2\\.js",
            "cookies": 0.000123,
            "fingerprinting": 1,
            "subdomains": [
                "a"
            ],
            "apis": {
                "Navigator.prototype.userAgent": 23,
                "Date.prototype.getTime": 25,
                "window.innerWidth": 18,
                "Document.cookie setter": 18
            },
            "sites": 25,
            "prevalence": 0.00017,
            "cnames": [],
            "responseHashes": [
                "db7052ffd93d212b277e35a3ddf323f9dcbed031916068fbe03dfa99502202ba"
            ],
            "type": "Script",
            "firstPartyCookies": {},
            "firstPartyCookiesSent": {},
            "exampleSites": [
                "tempel.link",
                "xnxvideosex.com",
                "matureclub.com",
                "www.pornv.xxx",
                "deepsukebe.io",
                "amateurpornpics.pro",
                "www.atubecn1.com",
                "myamateurgals.com",
                "www.sexfreehd.xxx",
                "ww9.readonepiece.com",
                "hdsex2.com",
                "www.sexvideo12.com",
                "gfpicsforfree.com",
                "videosection.com",
                "hdsex.org",
                "www.atube.sex",
                "www.sexmxxx.pro",
                "www.atube.xxx",
                "mangaeffect.com",
                "cdn.deepsukebe.io"
            ]
        },
        {
            "rule": "exdynsrv\\.com\\/splash\\.php",
            "cookies": 0.000197,
            "fingerprinting": 0,
            "subdomains": [
                "syndication"
            ],
            "apis": {},
            "sites": 30,
            "prevalence": 0.000204,
            "cnames": [],
            "responseHashes": [
                "0c2d0e5ec507f78869bb640717125bd65132315fd973ecfeeb672d61e7456dfb",
                "a2f78f2b1e2cba1bddb215f483676aef67b46462ac43affa32d8ae1437366303",
                "3aad387bb57cb9621d4fd15f50c4a8010d6cce31f4d264140d080564d058005e",
                "9b8380930ee9e0c5190914c88538b32768ff7416ff8d1c0de04274190902221d",
                "d1641669ff76b92d8127c978465e984a0e4418f278f6a2baa2fee5b4c2a704e6",
                "998fda1e0a020da5023886b85f4d84db1af87a6c0a8b2b8887e3fae1a9e50c34",
                "2ec743b88bd946ec607548c3b5b1173f180f75a1301861fb478401fcb6c2a253",
                "82cd8c2a7c9203294af8ad6ebf89b32a0728dc26647f76305282f6dadc63f7b1",
                "0bca11b67cc31b14d949f5d2d086b468439869e5e351e0cadb52e44f11089805",
                "fe83b9807bae309ed93c156af9b4a9bbc1d4709d52d640d3807c5469206d229f",
                "f9d8124bb041f5b288ee8e953c89a0900ae732d5e93ef4d25e031e39c9593d99",
                "3a4e3386cf04776f66121a786adab789d9b800632283aa91c52b7a3998c05079",
                "8e32d1e8eff4ad81cf9f70e99828afd49dcf8f835f0f47f083a11891ec7c7dc2",
                "e27539ed3eb60a806dd103a72817f5bcc760589ea3185ce59f3f805234d9333b",
                "150e1305ebfbe0777719b8def8d9e898ec160bbf218d820bf78f7dc7b0ae3882",
                "d3b379114bb299dc85aa130aca8bd3809cc12122427c65609e740ea30b7093d2",
                "0f06371a2eaec51689d6e008bfb2e137dc47a29fb3095fc54804de29da064b61",
                "95505d46e8d766e77dc3bed86c52662f8b2157637689283de3cce6fe27e0cead",
                "428ab6a8da70598fdae8879f665c16fa967ee6c1ba1abaf559c3c8e5511930f9",
                "87e03b9e9a0a6f75646c1be7d2c253fba5586e576f99ffd3fa24ba24a8844faa",
                "864e66c7393c173fc37019c44793f5eca0e79df0d86fc142153427109bfc1e13",
                "208876eb4c4bfe0b39ac2402e63bbcba744e10b83608a6844f2881cdaf35b0c0",
                "624caa5442b75f8a77e2346775b9f31f65090a5b25fe494152db94f69182ef10",
                "a019e35f11dd1214049804d1fefc58d8d8bcd1609ed52274694e67d33dcab414",
                "328d412e23274d2fd8b6469e6cfc633e3a5cca36ffe09b5d0d0ce8c18f586765",
                "b9e776d2a872ba5388b8d24fb00ef146a7d4b81a17e118207093d30a7064edbe"
            ],
            "type": "XHR",
            "firstPartyCookies": {},
            "firstPartyCookiesSent": {
                "lotame_domain_check": 0.000006806888571234089
            },
            "exampleSites": [
                "thepiratebay.org",
                "hdsex2.com",
                "mangaeffect.com",
                "readfreecomics.com",
                "www.xxxvideor.com",
                "www.atube.sex",
                "cdn.deepsukebe.io",
                "deepsukebe.io",
                "amateurpornpics.pro",
                "ww1.onepiecemangafree.com",
                "www.sexmxxx.pro",
                "www.fullhdxxx.com",
                "hdsex.org",
                "www.sexfreehdin.pro",
                "www.pornv.xxx",
                "gfpicsforfree.com",
                "www.farthub.com",
                "www.atubecn1.com",
                "myamateurgals.com",
                "videosection.com"
            ]
        },
        {
            "rule": "exdynsrv\\.com\\/ads\\.js",
            "cookies": 0,
            "fingerprinting": 1,
            "subdomains": [
                "a"
            ],
            "apis": {
                "Date.prototype.getTime": 4,
                "Screen.prototype.width": 4,
                "Screen.prototype.height": 4
            },
            "sites": 4,
            "prevalence": 0.0000272,
            "cnames": [],
            "responseHashes": [
                "e1da8a7084d3171a06501700b818317fb9c8162945a87bf184ce2abc58e3d08a"
            ],
            "type": "Script",
            "firstPartyCookies": {},
            "firstPartyCookiesSent": {},
            "exampleSites": [
                "myvidster.com",
                "api.myvidster.com",
                "backpagelocals.com",
                "www.myvidster.com"
            ]
        },
        {
            "rule": "exdynsrv\\.com\\/ads-iframe-display\\.php",
            "cookies": 0.0000272,
            "fingerprinting": 0,
            "subdomains": [
                "syndication"
            ],
            "apis": {},
            "sites": 4,
            "prevalence": 0.0000272,
            "cnames": [],
            "responseHashes": [
                "101d99d2d77d1822eb4ba5adc241d1f002c7841252b0fbbb175a1243d0452bf2",
                "4fbb41ab56f71135d6b00b581743e841ed5df9b13651b6d7183fbe1d8a19d4e0"
            ],
            "type": "Document",
            "firstPartyCookies": {},
            "firstPartyCookiesSent": {},
            "exampleSites": [
                "myvidster.com",
                "api.myvidster.com",
                "backpagelocals.com",
                "www.myvidster.com"
            ]
        },
        {
            "rule": "exdynsrv\\.com\\/popunder1000\\.js",
            "cookies": 0,
            "fingerprinting": 3,
            "subdomains": [
                "a"
            ],
            "apis": {
                "Navigator.prototype.userAgent": 9,
                "Navigator.prototype.mimeTypes": 9,
                "window.innerWidth": 9,
                "window.innerHeight": 9,
                "window.screenX": 9,
                "window.screenLeft": 9,
                "window.screenY": 9,
                "window.screenTop": 9,
                "Date.prototype.getTime": 10,
                "window.localStorage": 9
            },
            "sites": 10,
            "prevalence": 0.0000681,
            "cnames": [],
            "responseHashes": [
                "1dd92bc4a147f9a7f8d6e4a3d82b80bf419616abb729a3ce5fe041c595b099e4"
            ],
            "type": "Script",
            "firstPartyCookies": {},
            "firstPartyCookiesSent": {},
            "exampleSites": [
                "bravewords.com",
                "erotiga.net",
                "movies.waploaded.com",
                "music.waploaded.com",
                "oshinoko.net",
                "readherooacademia.online",
                "tioanime.com",
                "toonfr.com",
                "ww1.onepiecemangafree.com",
                "www.carlsguides.com"
            ]
        },
        {
            "rule": "exdynsrv\\.com\\/ad-provider\\.js",
            "cookies": 0.00000681,
            "fingerprinting": 1,
            "subdomains": [
                "a"
            ],
            "apis": {
                "Navigator.prototype.userAgent": 18,
                "Navigator.prototype.language": 17,
                "Date.prototype.getTime": 32,
                "window.innerHeight": 6,
                "window.innerWidth": 6,
                "Document.cookie getter": 1,
                "Document.cookie setter": 1
            },
            "sites": 37,
            "prevalence": 0.000252,
            "cnames": [],
            "responseHashes": [
                "7b258645c0442dff8ba8172ad126db0a5de73b0f293b30e9ae98fae10dec369c"
            ],
            "type": "Script",
            "firstPartyCookies": {
                "zone-cap-4835774": {
                    "ttl": 362,
                    "length": 1,
                    "prevalence": 0.000006806888571234089,
                    "uniqueness": 1
                }
            },
            "firstPartyCookiesSent": {},
            "exampleSites": [
                "justpicsplease.com",
                "www.homemoviestube.com",
                "xxxpicz.com",
                "manhwaindo.id",
                "www.amateurporn.me",
                "www.mypornhere.com",
                "pmatehunter.com",
                "myav.sbs",
                "hentai2w.com",
                "www.metarthunter.com",
                "www.elitebabes.com",
                "vercomicsporno.com",
                "tempel.link",
                "www.freexcafe.com",
                "www.sankakucomplex.com",
                "vermangasporno.com",
                "www1.verhentai.top",
                "mangabuddy.com",
                "www.mma-core.com",
                "hentaihere.com"
            ]
        },
        {
            "rule": "exdynsrv\\.com\\/v1\\/api\\.php",
            "cookies": 0.000211,
            "fingerprinting": 0,
            "subdomains": [
                "syndication"
            ],
            "apis": {},
            "sites": 35,
            "prevalence": 0.000238,
            "cnames": [],
            "responseHashes": [
                "4a410da209c9946f046fea7a8806b5ca5ff967c4e510dbef2596d64b64ebbcc0",
                "397271e05248ab58b425b7a9d0553c73c16de40d18c8e7a21ee3a86b3f380e80",
                "1939a127143f24aabecdebc42c2ef1ce030ba7c268b8485be50ae514fafc0d98",
                "ae0dcd29d6f27a30652bd88bb2f9904d7f354b3993e4b297a85804ebd71adb65",
                "4a9f5153c6d8c3418f00f0547ec64d6598311564e0a09dd00305903c61a4ca02",
                "e455b6d7d6ecb8db9dea2e1028107b8fc2594fbb51506b557c4d7f9eb7096564",
                "ac6e99f329d85ed273737331b211b16542200cf0eda4e49b69bbfac0aa419792",
                "f1a1b1b155b00e9f1e0a295756851ad3bf0cc255f6d59ea98567ad4b13447ab3",
                "8de9b6f4dda10095439884c5975b77339b4fd4cb4730e03dba6d94df0550548f",
                "383e7a9d7e4cc7bd10d001394deb8b5ad09b30a8f05fb1a37679a0c41f3a61e5",
                "d07e30592ceb107feb81df630ac9d72ab5655ab4e4aa0aec3e7dafcf05d33ab4",
                "32612210ade4f2f0ea7d3ca10255e4431fc30c8a8e192ec524665591b6ddc830",
                "a69c7b6042c0bdf694671f529c5159dbf4cbbd08e5b6665091d0b6e1e77418a1",
                "2898ab389db7e92e3aa15246d997af81a9dbdd28a0c1c62feb5331800eed3fc2",
                "61cf7ee5f97d33b01c5fb32a2f22748c71ddaef521390c6ad369eabc146bae83",
                "cb6e10807cde519f24d3bb9116c33a2957a1680863323bbde315949cd67ff86c",
                "b0b10c26446b0c3abb1b25e096efe6ae44b162e55415d5481a00c93be931a667",
                "7f1664de0000d3bab9694eee164ed924e94e40f1885b8252306fd8e72fcd4ca5",
                "9a67d655a8b975788e384522f7a5a3679b1d6aa76303d7970a43bc356e9eea7c",
                "b3a1f53f8197af5a15428abe0f31975d0c92964d7d760459ff9ae213dba6b425",
                "3e468d1f1dc3459aa03c164ecd2fec01f2cc62a29c3f49f1b6001312e04993de",
                "87894164b7082d310803f6ab0047512d8ed36b751bd59cb521a4b69bf7445f1b",
                "c8c06d7318bd3c0d0b67bb90d3df0668abda7ba489b0dce16fc459094065454c",
                "996df6472a6b23e4a2f0a423331b74a847b31631eb19941c3871219b01339008",
                "fde99fb41a658505efb68e704fbe89ad3f66ea79ab8eb7b3039a848ae85571f7",
                "dfdaa6f0f5fec0ed14212ad76c1d60dc0bfa411fbb5fddc092e03e09d965e9ee",
                "350a7a9da89052376d00799baffee470f96eff3dc27591a77b968f1e0d73da9d",
                "b5e963c28ef29d244fba843e25baaa07467be1de7ba2649e186a65196b6a7953",
                "3d736dd3f3b789815ca196c4be247644b84c3e199df84e266d957e572016f0ef",
                "52f3baa129e6328b64962b5258dc6030fea32e876fa51f5851b964fc39d17ced",
                "9ccce69ae3e2b838d58eec44dcb402cdad995643ad483e80c95c62ddde64c948",
                "0c4dc4cfb1fb58ff0bfe7772434c7f8759ad598988e5a248f7d16ed29d77cfdc",
                "c9ada5c0eb7eade0e6e740437db00ec764bf8637e847cb3c14cffacb697e89bc",
                "853f588cfe9a7b22e9c677291bc27fde2c77d35864b3b0f49ec8bed39f40ad6c"
            ],
            "type": "XHR",
            "firstPartyCookies": {},
            "firstPartyCookiesSent": {},
            "exampleSites": [
                "justpicsplease.com",
                "www.homemoviestube.com",
                "v4.voiranime.com",
                "doodstream.link",
                "manhwaindo.id",
                "hentairox.com",
                "hentai2read.com",
                "chapmanganato.com",
                "www.xarthunter.com",
                "clipsbai.com",
                "tempel.link",
                "vermangasporno.com",
                "hentai2w.com",
                "www.elitebabes.com",
                "sisterporn.tv",
                "myav.sbs",
                "www.femjoyhunter.com",
                "toonx.net",
                "www.mypornhere.com",
                "xxxpicz.com"
            ]
        },
        {
            "rule": "exdynsrv\\.com\\/cimp\\.php",
            "cookies": 0.000238,
            "fingerprinting": 0,
            "subdomains": [
                "syndication"
            ],
            "apis": {},
            "sites": 35,
            "prevalence": 0.000238,
            "cnames": [],
            "responseHashes": [
                "e3b0c44298fc1c149afbf4c8996fb92427ae41e4649b934ca495991b7852b855"
            ],
            "type": "XHR",
            "firstPartyCookies": {},
            "firstPartyCookiesSent": {},
            "exampleSites": [
                "justpicsplease.com",
                "www.homemoviestube.com",
                "v4.voiranime.com",
                "vermangasporno.com",
                "toonfr.com",
                "www.ftvhunter.com",
                "www1.verhentai.top",
                "toonx.net",
                "tempel.link",
                "doodstream.link",
                "www.elitebabes.com",
                "hentai2w.com",
                "hentai2read.com",
                "hentairox.com",
                "v5.voiranime.com",
                "www.farthub.com",
                "www.freexcafe.com",
                "pmatehunter.com",
                "xxxpicz.com",
                "www.metarthunter.com"
            ]
        },
        {
            "rule": "exdynsrv\\.com\\/iframe\\.php",
            "cookies": 0,
            "fingerprinting": 0,
            "subdomains": [
                "a"
            ],
            "apis": {},
            "sites": 16,
            "prevalence": 0.000109,
            "cnames": [],
            "responseHashes": [
                "a3ff539637c9c0280a58d61c62e4c75a06cc81e4133c6f3a1e933e7fecf6ffe0",
                "0aeac6cca129ef139dad9f8f4105b25b0415422010a3bca2713dc7a00c43dfae",
                "407a3a73edbae306a8ff56a02876b2862580b726d8c9e939a2c9dba4c79aa994",
                "bed28b43157f9513f6d662a83409cf345543fe4d497a81a6e4c317370e747a57",
                "b37e3467bde48c7953e6d6eab743fd90e9408612afe811f88c6db5988d19f500",
                "080eab462626743a682e1be5cc6649b64958b4d09bceea3f422824f09d6d16a3",
                "9b7a3dfb5d1f85272a798f172789eb6284e8a50cfbed83e3292e39ae70b59b47",
                "e2acaaef13c7b4a08a76ea891e4ad0823225439c69d48296ac8b9f729e360e82",
                "df770ebb34e5606e6025fd376bf0a2d80d6ddb757728ca4f0414e03a2ec8dca5"
            ],
            "type": "Document",
            "firstPartyCookies": {},
            "firstPartyCookiesSent": {},
            "exampleSites": [
                "clipsbai.com",
                "hentairox.com",
                "justpicsplease.com",
                "megapornx.com",
                "myav.sbs",
                "readfreecomics.com",
                "sisterporn.tv",
                "toonx.net",
                "vercomicsporno.com",
                "vermangasporno.com",
                "www.amateurporn.me",
                "www.freexcafe.com",
                "www.homemoviestube.com",
                "www.mypornhere.com",
                "www1.verhentai.top",
                "xxxpicz.com"
            ]
        },
        {
            "rule": "exdynsrv\\.com\\/build-iframe-js-url\\.js",
            "cookies": 0,
            "fingerprinting": 0,
            "subdomains": [
                "a"
            ],
            "apis": {},
            "sites": 16,
            "prevalence": 0.000109,
            "cnames": [],
            "responseHashes": [
                "fcf4e9788d44d0e4502ca13a894a5c393f6f82c56a62e81afa45721551d7dea7",
                "4f1b1f214c6b60cf3984050fe249b66768d700beb1b51f7fbc1596b27a2a398e",
                "ef9ce96957b829cec8425eba3d6552e0c6e92a6745810d99774a416acb4ff242",
                "fa437eff1c00b4c07142bccb0d08da544b5b569b2f135f145e79d8a67dc08282",
                "6de034a62437de25d41362bee62acdf2d1583c60e3ce7b9c80de375b41e1de69",
                "248a1b6d46165d5082820751c84ee3bb2d049d7704e64491de38d142793cee68",
                "f8a8b793200276e784453781c2d8146f109d8a96b038c9ffc240a3c3cd1ead4f",
                "478f094315f8c149c5318019b6296c06c3bf1adb1c23486de01b4dbc2f5b907b",
                "52932301e9040c7451f8240e375153269bd649146a70f36d60b1c560ef22b754"
            ],
            "type": "Script",
            "firstPartyCookies": {},
            "firstPartyCookiesSent": {},
            "exampleSites": [
                "clipsbai.com",
                "hentairox.com",
                "justpicsplease.com",
                "megapornx.com",
                "myav.sbs",
                "readfreecomics.com",
                "sisterporn.tv",
                "toonx.net",
                "vercomicsporno.com",
                "vermangasporno.com",
                "www.amateurporn.me",
                "www.freexcafe.com",
                "www.homemoviestube.com",
                "www.mypornhere.com",
                "www1.verhentai.top",
                "xxxpicz.com"
            ]
        },
        {
            "rule": "exdynsrv\\.com\\/iframe\\.js",
            "cookies": 0,
            "fingerprinting": 0,
            "subdomains": [
                "a"
            ],
            "apis": {},
            "sites": 16,
            "prevalence": 0.000109,
            "cnames": [],
            "responseHashes": [
                "be7281f714c4eba717932fde75dde15f3b817f3cad2d604a2f4b4e7c2ab7d55b",
                "2f65b4f988019f08a1050db98c2fb1b019b0c25bb287eec5d879c464a7802909",
                "e702e9f8a64e7f48ce70dd582789b8330746c56ccc1231e539f7d298c9252c14",
                "87f040d22338920640978ff87248d1ceda77c8fbdcfe6764395791915e026380",
                "6deaa7892d008b4a356da8cbe91acbb4df7cdfe32e40b03011743fb70f69ee98",
                "4b8087f55395d873b216270629edff7eef79bacbf26bac339109e16232696899",
                "500157e2aa338f1f3b89df7cbcffb68f5a72444e158c4dcd7b12e0544899c74a",
                "c2853222e09a83cae3cea373725a0f8fa553c5c47a01cc78f96304ad2a4d68aa",
                "582d9a870f27b76eee81d99b5c30f59ee9b37f641621183e87e2a4e1ebb3d68f"
            ],
            "type": "Script",
            "firstPartyCookies": {},
            "firstPartyCookiesSent": {},
            "exampleSites": [
                "clipsbai.com",
                "hentairox.com",
                "justpicsplease.com",
                "megapornx.com",
                "myav.sbs",
                "readfreecomics.com",
                "sisterporn.tv",
                "toonx.net",
                "vercomicsporno.com",
                "vermangasporno.com",
                "www.amateurporn.me",
                "www.freexcafe.com",
                "www.homemoviestube.com",
                "www.mypornhere.com",
                "www1.verhentai.top",
                "xxxpicz.com"
            ]
        },
        {
            "rule": "exdynsrv\\.com\\/splash\\.php",
            "cookies": 0.0000272,
            "fingerprinting": 1,
            "subdomains": [
                "syndication"
            ],
            "apis": {
                "Navigator.prototype.userAgent": 2,
                "Document.cookie getter": 2,
                "Document.cookie setter": 1
            },
            "sites": 4,
            "prevalence": 0.0000272,
            "cnames": [],
            "responseHashes": [
                "844b679a266ac72357c509572ee09ab9ec6ea28e3f22607664d42dfbbeea1b9e",
                "e3b0c44298fc1c149afbf4c8996fb92427ae41e4649b934ca495991b7852b855",
                "41621c4c927435284741bf08d1e1114663583b427a9c75d67e1dd9a5ba970ae8"
            ],
            "type": "Script",
            "firstPartyCookies": {
                "zone-cap-4867358": {
                    "ttl": 21601,
                    "length": 1,
                    "prevalence": 0.000006806888571234089,
                    "uniqueness": 1
                }
            },
            "firstPartyCookiesSent": {},
            "exampleSites": [
                "doodstream.link",
                "outputter.io",
                "tempel.link",
                "toonfr.com"
            ]
        },
        {
            "rule": "exdynsrv\\.com\\/tag\\.php",
            "cookies": 0.0000408,
            "fingerprinting": 0,
            "subdomains": [
                "syndication"
            ],
            "apis": {},
            "sites": 6,
            "prevalence": 0.0000408,
            "cnames": [],
            "responseHashes": [
                "e3b0c44298fc1c149afbf4c8996fb92427ae41e4649b934ca495991b7852b855"
            ],
            "type": "Image",
            "firstPartyCookies": {},
            "firstPartyCookiesSent": {},
            "exampleSites": [
                "fuqqt.com",
                "javhd.com",
                "phonerotica.com",
                "www.sexlikereal.com",
                "www.vivid.com",
                "xxxgames.games"
            ]
        },
        {
            "rule": "exdynsrv\\.com\\/video-slider\\.js",
            "cookies": 0,
            "fingerprinting": 1,
            "subdomains": [
                "a"
            ],
            "apis": {
                "Document.cookie getter": 3
            },
            "sites": 3,
            "prevalence": 0.0000204,
            "cnames": [],
            "responseHashes": [
                "09c3f9e17786ca3941ca690c4523a3b4f7c68f861452ebad8e31f7a637463018"
            ],
            "type": "Script",
            "firstPartyCookies": {},
            "firstPartyCookiesSent": {},
            "exampleSites": [
                "oshinoko.net",
                "readfreecomics.com",
                "ww1.onepiecemangafree.com"
            ]
        },
        {
            "rule": "exdynsrv\\.com\\/ad-provider\\.js",
            "cookies": 0,
            "fingerprinting": 1,
            "subdomains": [
                "a"
            ],
            "apis": {
                "Navigator.prototype.userAgent": 5,
                "Navigator.prototype.language": 5,
                "Date.prototype.getTime": 6,
                "window.innerHeight": 6,
                "window.innerWidth": 6
            },
            "sites": 6,
            "prevalence": 0.0000408,
            "cnames": [],
            "responseHashes": [],
            "type": "Fetch",
            "firstPartyCookies": {},
            "firstPartyCookiesSent": {},
            "exampleSites": [
                "pmatehunter.com",
                "www.elitebabes.com",
                "www.femjoyhunter.com",
                "www.ftvhunter.com",
                "www.metarthunter.com",
                "www.xarthunter.com"
            ]
        }
    ],
    "categories": [
        "Ad Motivated Tracking",
        "Advertising"
    ],
    "performance": {},
    "cookies": 0.00079,
    "topInitiators": [
        {
            "domain": "first party",
            "prevalence": 0.4074074074074074
        },
        {
            "domain": "topvidstore.com",
            "prevalence": 0.05555555555555555
        },
        {
            "domain": "reryn2ce.com",
            "prevalence": 0.05555555555555555
        },
        {
            "domain": "hwcdn.net",
            "prevalence": 0.05092592592592592
        },
        {
            "domain": "g--o.info",
            "prevalence": 0.05092592592592592
        },
        {
            "domain": "hotmovstore.com",
            "prevalence": 0.046296296296296294
        },
        {
            "domain": "exoclick.com",
            "prevalence": 0.037037037037037035
        },
        {
            "domain": "letstry69.xyz",
            "prevalence": 0.037037037037037035
        },
        {
            "domain": "songtopbrand.com",
            "prevalence": 0.037037037037037035
        },
        {
            "domain": "vidogrey.fun",
            "prevalence": 0.027777777777777776
        }
    ],
    "types": {
        "Script": 115,
        "XHR": 100,
        "Document": 20,
        "Image": 6,
        "Fetch": 6
    },
    "nameservers": [
        "dns2.cloudns.net",
        "dns1.cloudns.net",
        "sec2.rcode0.net",
        "sec1.rcode0.net"
    ]
}