{
    "domain": "inadequateinadmissibleoblige.com",
    "owner": {},
    "source": [
        "DuckDuckGo-US"
    ],
    "prevalence": 0.000163,
    "sites": 24,
    "subdomains": [],
    "cnames": [],
    "fingerprinting": 0,
    "resources": [
        {
            "rule": "inadequateinadmissibleoblige\\.com\\/cd\\/2f\\/ce\\/cd2fce2180c73993233473d1c443530d\\.js",
            "cookies": 0,
            "fingerprinting": 0,
            "subdomains": [],
            "apis": {},
            "sites": 24,
            "prevalence": 0.000163,
            "cnames": [],
            "responseHashes": [
                "e3b0c44298fc1c149afbf4c8996fb92427ae41e4649b934ca495991b7852b855"
            ],
            "type": "Script",
            "firstPartyCookies": {},
            "firstPartyCookiesSent": {},
            "exampleSites": [
                "porn-leaks.com",
                "thisisnude.com",
                "ipornpic.com",
                "leakshemale.com",
                "fapnudes.com",
                "babe.wtf",
                "jihadcelebs.com",
                "leaksextape.com",
                "thegirls.info",
                "pornpiz.com",
                "sextape.pro",
                "girlsleak.com",
                "webfapfap.com",
                "thecelebrity.biz",
                "fappingxxx.com",
                "celebrity-sextape.com",
                "yespornpic.com",
                "jihadceleb.com",
                "porns.photos",
                "thepornpic.com"
            ]
        }
    ],
    "categories": [],
    "performance": {},
    "cookies": 0,
    "topInitiators": [
        {
            "domain": "adsxyz.com",
            "prevalence": 0.6071428571428571
        },
        {
            "domain": "first party",
            "prevalence": 0.39285714285714285
        }
    ],
    "types": {
        "Script": 24
    },
    "nameservers": [
        "ns2.publicdnsservice.com",
        "ns3.publicdnsservice.com",
        "ns4.publicdnsservice.com",
        "ns1.publicdnsservice.com"
    ]
}